README.md
hp_report_portal/__init__.py
hp_report_portal/report_portal.py
hp_report_portal-0.1.0.dist-info/WHEEL
hp_report_portal-0.1.0.dist-info/METADATA
hp_report_portal-0.1.0.dist-info/RECORD
