Metadata-Version: 2.1
Name: hp-report-portal
Version: 0.1.0
Summary: behave report portal hook plugin
Home-page: https://github.com/dunossauro/report-portal-hook-plugin/
License: MIT
Author: dunossauro
Author-email: mendesxeduardo@gmail.com
Requires-Python: >=3.5,<4.0
Classifier: License :: OSI Approved :: MIT License
Classifier: Programming Language :: Python :: 3
Classifier: Programming Language :: Python :: 3.5
Classifier: Programming Language :: Python :: 3.6
Classifier: Programming Language :: Python :: 3.7
Requires-Dist: hook-plug (>=0.0.1,<0.0.2)
Requires-Dist: reportportal-client (>=3.2,<4.0)
